legos/__init__.py
legos/fact_sphere.py
legos/facts.yaml
legos.fact_sphere-0.1.1.dist-info/METADATA
legos.fact_sphere-0.1.1.dist-info/RECORD
legos.fact_sphere-0.1.1.dist-info/WHEEL
legos.fact_sphere-0.1.1.dist-info/top_level.txt
